AUTHORS
CHANGELOG
LICENSE
MANIFEST.in
README
README.rst
setup.py
django_documents.egg-info/PKG-INFO
django_documents.egg-info/SOURCES.txt
django_documents.egg-info/dependency_links.txt
django_documents.egg-info/not-zip-safe
django_documents.egg-info/requires.txt
django_documents.egg-info/top_level.txt
documents/__init__.py
documents/admin.py
documents/autocomplete_light_registry.py
documents/exceptions.py
documents/forms.py
documents/models.py
documents/settings.py
documents/signals.py
documents/tests.py
documents/urls.py
documents/views.py
documents/widgets.py
documents/fixtures/test_fixtures.json
documents/migrations/0001_initial.py
documents/migrations/__init__.py
documents/templatetags/__init__.py
documents/templatetags/documents_tags.py