Metadata-Version: 1.1
Name: django-documents
Version: 0.0.3
Summary: Attach documents to django models
Home-page: https://github.com/yourlabs/django-documents
Author: James Pic
Author-email: jamespic@gmail.com
License: MIT
Keywords: django document
Platform: UNKNOWN
Classifier: Development Status :: 3 - Alpha
Classifier: Environment :: Web Environment
Classifier: Framework :: Django
Classifier: Intended Audience :: Developers
Classifier: License :: OSI Approved :: MIT License
Classifier: Operating System :: OS Independent
Classifier: Programming Language :: Python
Classifier: Programming Language :: Python :: 2
Classifier: Topic :: Internet :: WWW/HTTP
Classifier: Topic :: Software Development :: Libraries :: Python Modules
